sysmap/__init__.py
sysmap/cli.py
sysmap/core/__init__.py
sysmap/core/config.py
sysmap/core/scanner.py
sysmap/exporters/__init__.py
sysmap/exporters/base.py
sysmap/exporters/csv_exporter.py
sysmap/exporters/html_exporter.py
sysmap/exporters/json_exporter.py
sysmap/exporters/markdown.py
sysmap/exporters/yaml_exporter.py
sysmap/utils/__init__.py
sysmap/utils/diff.py
sysmap/utils/watch.py
sysmap-0.1.0.dist-info/licenses/LICENSE
sysmap-0.1.0.dist-info/METADATA
sysmap-0.1.0.dist-info/WHEEL
sysmap-0.1.0.dist-info/entry_points.txt
sysmap-0.1.0.dist-info/top_level.txt
sysmap-0.1.0.dist-info/RECORD
